git_filter_repo_for_toprepo.py
git_toprepo.py
git_toprepo-0.1.0rc10.dist-info/LICENSE
git_toprepo-0.1.0rc10.dist-info/METADATA
git_toprepo-0.1.0rc10.dist-info/WHEEL
git_toprepo-0.1.0rc10.dist-info/entry_points.txt
git_toprepo-0.1.0rc10.dist-info/RECORD
