Metadata-Version: 2.3
Name: git-toprepo
Version: 0.1.0rc10
Summary: git-submodule made easy with git-toprepo
License: GPL-3.0-only
Keywords: git,submodule,monorepo,toprepo,superrepo
Author: Fredrik Medley
Author-email: fredrik@meroton.com
Requires-Python: >=3.8,<4.0
Classifier: License :: OSI Approved :: GNU General Public License v3 (GPLv3)
Classifier: Programming Language :: Python :: 3
Classifier: Programming Language :: Python :: 3.8
Classifier: Programming Language :: Python :: 3.9
Classifier: Programming Language :: Python :: 3.10
Classifier: Programming Language :: Python :: 3.11
Classifier: Programming Language :: Python :: 3.12
Classifier: Programming Language :: Python :: 3.13
